postgresql_geometry/__init__.py
postgresql_geometry/datastructures.py
postgresql_geometry/django/__init__.py
postgresql_geometry/django/models/__init__.py
postgresql_geometry/django/models/fields.py
postgresql_geometry/django/models/functions.py
postgresql_geometry/django/models/operations.py
postgresql_geometry/faker/__init__.py
postgresql_geometry/faker/providers.py
postgresql_geometry/rest_framework/__init__.py
postgresql_geometry/rest_framework/fields.py
postgresql_geometry-0.1.1.dist-info/METADATA
postgresql_geometry-0.1.1.dist-info/WHEEL
postgresql_geometry-0.1.1.dist-info/RECORD
